{"cameraMode":{"drawMode":0,"name":"Shaded","section":"Shading Mode"},"sceneLighting":false,"audioPlay":false,"sceneViewState":{"m_AlwaysRefresh":false,"showFog":true,"showSkybox":false,"showFlares":true,"showImageEffects":true,"showParticleSystems":true,"showVisualEffectGraphs":true,"m_FxEnabled":true},"in2DMode":false,"pivot":{"x":2.859999895095825,"y":0.8960000276565552,"z":-0.21299999952316285},"rotation":{"x":-0.0039162603206932549,"y":0.9910122156143189,"z":-0.13037997484207154,"w":-0.0297513697296381},"size":1.1902656555175782,"orthographic":false}